mcp3008.py
mcp3008-1.0.1.dist-info/LICENSE.md
mcp3008-1.0.1.dist-info/METADATA
mcp3008-1.0.1.dist-info/WHEEL
mcp3008-1.0.1.dist-info/top_level.txt
mcp3008-1.0.1.dist-info/RECORD
