Metadata-Version: 2.1
Name: mcp3008
Version: 1.0.1
Summary: RPi_mcp3008 is a library to listen to the MCP3008 A/D converter chip, as described in the datasheet.
Home-page: https://github.com/luxedo/RPi_mcp3008
Author: Luiz Eduardo Nishino Gomes do Amaral
Author-email: luizamaral306@gmail.com
License: GPL3
Keywords: RPi MCP3008 SPI interface
Classifier: Development Status :: 5 - Production/Stable
Classifier: Intended Audience :: Developers
Classifier: Topic :: System :: Hardware
Classifier: Topic :: Software Development :: Libraries :: Python Modules
Classifier: License :: OSI Approved :: GNU General Public License v3 or later (GPLv3+)
Classifier: Programming Language :: Python :: 2
Classifier: Programming Language :: Python :: 2.6
Classifier: Programming Language :: Python :: 2.7
Classifier: Programming Language :: Python :: 3
Classifier: Programming Language :: Python :: 3.2
Classifier: Programming Language :: Python :: 3.3
Classifier: Programming Language :: Python :: 3.4
Classifier: Programming Language :: Python :: 3.5
Classifier: Programming Language :: Python :: 3.6
Classifier: Programming Language :: Python :: 3.7
Classifier: Programming Language :: Python :: 3.8
License-File: LICENSE.md
Requires-Dist: spidev
